[
  {
    "name": "Bath",
    "country": "United Kingdom",
    "region": "Europe"
  },
  {
    "name": "York",
    "country": "United Kingdom",
    "region": "Europe"
  },
  {
    "name": "Belfast",
    "country": "United Kingdom",
    "region": "Europe"
  },
  {
    "name": "Nice",
    "country": "France",
    "region": "Europe"
  },
  {
    "name": "Lyon",
    "country": "France",
    "region": "Europe"
  },
  {
    "name": "Bordeaux",
    "country": "France",
    "region": "Europe"
  },
  {
    "name": "Strasbourg",
    "country": "France",
    "region": "Europe"
  },
  {
    "name": "Toulouse",
    "country": "France",
    "region": "Europe"
  },
  {
    "name": "Madrid",
    "country": "Spain",
    "region": "Europe"
  },
  {
    "name": "Seville",
    "country": "Spain",
    "region": "Europe"
  },
  {
    "name": "Valencia",
    "country": "Spain",
    "region": "Europe"
  },
  {
    "name": "Malaga",
    "country": "Spain",
    "region": "Europe"
  },
  {
    "name": "Granada",
    "country": "Spain",
    "region": "Europe"
  },
  {
    "name": "Bilbao",
    "country": "Spain",
    "region": "Europe"
  },
  {
    "name": "San Sebastian",
    "country": "Spain",
    "region": "Europe"
  },
  {
    "name": "Palma de Mallorca",
    "country": "Spain",
    "region": "Europe"
  },
  {
    "name": "Tenerife",
    "country": "Spain",
    "region": "Europe"
  },
  {
    "name": "Porto",
    "country": "Portugal",
    "region": "Europe"
  },
  {
    "name": "Faro",
    "country": "Portugal",
    "region": "Europe"
  },
  {
    "name": "Funchal",
    "country": "Portugal",
    "region": "Europe"
  },
  {
    "name": "Florence",
    "country": "Italy",
    "region": "Europe"
  },
  {
    "name": "Venice",
    "country": "Italy",
    "region": "Europe"
  },
  {
    "name": "Milan",
    "country": "Italy",
    "region": "Europe"
  },
  {
    "name": "Amalfi",
    "country": "Italy",
    "region": "Europe"
  },
  {
    "name": "Cinque Terre",
    "country": "Italy",
    "region": "Europe"
  },
  {
    "name": "Sicily",
    "country": "Italy",
    "region": "Europe"
  },
  {
    "name": "Bologna",
    "country": "Italy",
    "region": "Europe"
  },
  {
    "name": "Turin",
    "country": "Italy",
    "region": "Europe"
  },
  {
    "name": "Rotterdam",
    "country": "Netherlands",
    "region": "Europe"
  },
  {
    "name": "The Hague",
    "country": "Netherlands",
    "region": "Europe"
  },
  {
    "name": "Hamburg",
    "country": "Germany",
    "region": "Europe"
  },
  {
    "name": "Cologne",
    "country": "Germany",
    "region": "Europe"
  },
  {
    "name": "Frankfurt",
    "country": "Germany",
    "region": "Europe"
  },
  {
    "name": "Dresden",
    "country": "Germany",
    "region": "Europe"
  },
  {
    "name": "Geneva",
    "country": "Switzerland",
    "region": "Europe"
  },
  {
    "name": "Interlaken",
    "country": "Switzerland",
    "region": "Europe"
  },
  {
    "name": "Lucerne",
    "country": "Switzerland",
    "region": "Europe"
  },
  {
    "name": "Bruges",
    "country": "Belgium",
    "region": "Europe"
  },
  {
    "name": "Ghent",
    "country": "Belgium",
    "region": "Europe"
  },
  {
    "name": "Salzburg",
    "country": "Austria",
    "region": "Europe"
  },
  {
    "name": "Innsbruck",
    "country": "Austria",
    "region": "Europe"
  },
  {
    "name": "Galway",
    "country": "Ireland",
    "region": "Europe"
  },
  {
    "name": "Cork",
    "country": "Ireland",
    "region": "Europe"
  },
  {
    "name": "Luxembourg City",
    "country": "Luxembourg",
    "region": "Europe"
  },
  {
    "name": "Gothenburg",
    "country": "Sweden",
    "region": "Europe"
  },
  {
    "name": "Bergen",
    "country": "Norway",
    "region": "Europe"
  },
  {
    "name": "Tromso",
    "country": "Norway",
    "region": "Europe"
  },
  {
    "name": "Rovaniemi",
    "country": "Finland",
    "region": "Europe"
  },
  {
    "name": "Reykjavik",
    "country": "Iceland",
    "region": "Europe"
  },
  {
    "name": "Tallinn",
    "country": "Estonia",
    "region": "Europe"
  },
  {
    "name": "Riga",
    "country": "Latvia",
    "region": "Europe"
  },
  {
    "name": "Vilnius",
    "country": "Lithuania",
    "region": "Europe"
  },
  {
    "name": "Cesky Krumlov",
    "country": "Czech Republic",
    "region": "Europe"
  },
  {
    "name": "Gdansk",
    "country": "Poland",
    "region": "Europe"
  },
  {
    "name": "Wroclaw",
    "country": "Poland",
    "region": "Europe"
  },
  {
    "name": "Cluj-Napoca",
    "country": "Romania",
    "region": "Europe"
  },
  {
    "name": "Brasov",
    "country": "Romania",
    "region": "Europe"
  },
  {
    "name": "Plovdiv",
    "country": "Bulgaria",
    "region": "Europe"
  },
  {
    "name": "Belgrade",
    "country": "Serbia",
    "region": "Europe"
  },
  {
    "name": "Novi Sad",
    "country": "Serbia",
    "region": "Europe"
  },
  {
    "name": "Zagreb",
    "country": "Croatia",
    "region": "Europe"
  },
  {
    "name": "Dubrovnik",
    "country": "Croatia",
    "region": "Europe"
  },
  {
    "name": "Split",
    "country": "Croatia",
    "region": "Europe"
  },
  {
    "name": "Hvar",
    "country": "Croatia",
    "region": "Europe"
  },
  {
    "name": "Ljubljana",
    "country": "Slovenia",
    "region": "Europe"
  },
  {
    "name": "Lake Bled",
    "country": "Slovenia",
    "region": "Europe"
  },
  {
    "name": "Bratislava",
    "country": "Slovakia",
    "region": "Europe"
  },
  {
    "name": "Sarajevo",
    "country": "Bosnia and Herzegovina",
    "region": "Europe"
  },
  {
    "name": "Mostar",
    "country": "Bosnia and Herzegovina",
    "region": "Europe"
  },
  {
    "name": "Kotor",
    "country": "Montenegro",
    "region": "Europe"
  },
  {
    "name": "Budva",
    "country": "Montenegro",
    "region": "Europe"
  },
  {
    "name": "Skopje",
    "country": "North Macedonia",
    "region": "Europe"
  },
  {
    "name": "Ohrid",
    "country": "North Macedonia",
    "region": "Europe"
  },
  {
    "name": "Pristina",
    "country": "Kosovo",
    "region": "Europe"
  },
  {
    "name": "Santorini",
    "country": "Greece",
    "region": "Europe"
  },
  {
    "name": "Mykonos",
    "country": "Greece",
    "region": "Europe"
  },
  {
    "name": "Crete",
    "country": "Greece",
    "region": "Europe"
  },
  {
    "name": "Rhodes",
    "country": "Greece",
    "region": "Europe"
  },
  {
    "name": "Corfu",
    "country": "Greece",
    "region": "Europe"
  },
  {
    "name": "Thessaloniki",
    "country": "Greece",
    "region": "Europe"
  },
  {
    "name": "Antalya",
    "country": "Turkey",
    "region": "Europe"
  },
  {
    "name": "Cappadocia",
    "country": "Turkey",
    "region": "Europe"
  },
  {
    "name": "Bodrum",
    "country": "Turkey",
    "region": "Europe"
  },
  {
    "name": "Izmir",
    "country": "Turkey",
    "region": "Europe"
  },
  {
    "name": "Batumi",
    "country": "Georgia",
    "region": "Europe"
  },
  {
    "name": "Yerevan",
    "country": "Armenia",
    "region": "Europe"
  },
  {
    "name": "Baku",
    "country": "Azerbaijan",
    "region": "Europe"
  },
  {
    "name": "Tokyo",
    "country": "Japan",
    "region": "East Asia"
  },
  {
    "name": "Kyoto",
    "country": "Japan",
    "region": "East Asia"
  },
  {
    "name": "Osaka",
    "country": "Japan",
    "region": "East Asia"
  },
  {
    "name": "Hiroshima",
    "country": "Japan",
    "region": "East Asia"
  },
  {
    "name": "Nara",
    "country": "Japan",
    "region": "East Asia"
  },
  {
    "name": "Fukuoka",
    "country": "Japan",
    "region": "East Asia"
  },
  {
    "name": "Sapporo",
    "country": "Japan",
    "region": "East Asia"
  },
  {
    "name": "Okinawa",
    "country": "Japan",
    "region": "East Asia"
  },
  {
    "name": "Seoul",
    "country": "South Korea",
    "region": "East Asia"
  },
  {
    "name": "Busan",
    "country": "South Korea",
    "region": "East Asia"
  },
  {
    "name": "Jeju Island",
    "country": "South Korea",
    "region": "East Asia"
  },
  {
    "name": "Hong Kong",
    "country": "China",
    "region": "East Asia"
  },
  {
    "name": "Shanghai",
    "country": "China",
    "region": "East Asia"
  },
  {
    "name": "Beijing",
    "country": "China",
    "region": "East Asia"
  },
  {
    "name": "Chengdu",
    "country": "China",
    "region": "East Asia"
  },
  {
    "name": "Guilin",
    "country": "China",
    "region": "East Asia"
  },
  {
    "name": "Xi'an",
    "country": "China",
    "region": "East Asia"
  },
  {
    "name": "Taipei",
    "country": "Taiwan",
    "region": "East Asia"
  },
  {
    "name": "Kaohsiung",
    "country": "Taiwan",
    "region": "East Asia"
  },
  {
    "name": "Macau",
    "country": "China",
    "region": "East Asia"
  },
  {
    "name": "Ulaanbaatar",
    "country": "Mongolia",
    "region": "East Asia"
  },
  {
    "name": "Chiang Mai",
    "country": "Thailand",
    "region": "Southeast Asia"
  },
  {
    "name": "Phuket",
    "country": "Thailand",
    "region": "Southeast Asia"
  },
  {
    "name": "Koh Samui",
    "country": "Thailand",
    "region": "Southeast Asia"
  },
  {
    "name": "Krabi",
    "country": "Thailand",
    "region": "Southeast Asia"
  },
  {
    "name": "Pai",
    "country": "Thailand",
    "region": "Southeast Asia"
  },
  {
    "name": "Koh Phangan",
    "country": "Thailand",
    "region": "Southeast Asia"
  },
  {
    "name": "Singapore",
    "country": "Singapore",
    "region": "Southeast Asia"
  },
  {
    "name": "Penang",
    "country": "Malaysia",
    "region": "Southeast Asia"
  },
  {
    "name": "Langkawi",
    "country": "Malaysia",
    "region": "Southeast Asia"
  },
  {
    "name": "Malacca",
    "country": "Malaysia",
    "region": "Southeast Asia"
  },
  {
    "name": "Jakarta",
    "country": "Indonesia",
    "region": "Southeast Asia"
  },
  {
    "name": "Yogyakarta",
    "country": "Indonesia",
    "region": "Southeast Asia"
  },
  {
    "name": "Lombok",
    "country": "Indonesia",
    "region": "Southeast Asia"
  },
  {
    "name": "Komodo",
    "country": "Indonesia",
    "region": "Southeast Asia"
  },
  {
    "name": "Cebu",
    "country": "Philippines",
    "region": "Southeast Asia"
  },
  {
    "name": "Palawan",
    "country": "Philippines",
    "region": "Southeast Asia"
  },
  {
    "name": "Siargao",
    "country": "Philippines",
    "region": "Southeast Asia"
  },
  {
    "name": "Hoi An",
    "country": "Vietnam",
    "region": "Southeast Asia"
  },
  {
    "name": "Ha Long Bay",
    "country": "Vietnam",
    "region": "Southeast Asia"
  },
  {
    "name": "Sapa",
    "country": "Vietnam",
    "region": "Southeast Asia"
  },
  {
    "name": "Luang Prabang",
    "country": "Laos",
    "region": "Southeast Asia"
  },
  {
    "name": "Vientiane",
    "country": "Laos",
    "region": "Southeast Asia"
  },
  {
    "name": "Yangon",
    "country": "Myanmar",
    "region": "Southeast Asia"
  },
  {
    "name": "Bagan",
    "country": "Myanmar",
    "region": "Southeast Asia"
  },
  {
    "name": "New Delhi",
    "country": "India",
    "region": "South Asia"
  },
  {
    "name": "Goa",
    "country": "India",
    "region": "South Asia"
  },
  {
    "name": "Jaipur",
    "country": "India",
    "region": "South Asia"
  },
  {
    "name": "Varanasi",
    "country": "India",
    "region": "South Asia"
  },
  {
    "name": "Kerala",
    "country": "India",
    "region": "South Asia"
  },
  {
    "name": "Udaipur",
    "country": "India",
    "region": "South Asia"
  },
  {
    "name": "Agra",
    "country": "India",
    "region": "South Asia"
  },
  {
    "name": "Rishikesh",
    "country": "India",
    "region": "South Asia"
  },
  {
    "name": "Kolkata",
    "country": "India",
    "region": "South Asia"
  },
  {
    "name": "Bangalore",
    "country": "India",
    "region": "South Asia"
  },
  {
    "name": "Ella",
    "country": "Sri Lanka",
    "region": "South Asia"
  },
  {
    "name": "Galle",
    "country": "Sri Lanka",
    "region": "South Asia"
  },
  {
    "name": "Pokhara",
    "country": "Nepal",
    "region": "South Asia"
  },
  {
    "name": "Dhaka",
    "country": "Bangladesh",
    "region": "South Asia"
  },
  {
    "name": "Thimphu",
    "country": "Bhutan",
    "region": "South Asia"
  },
  {
    "name": "Male",
    "country": "Maldives",
    "region": "South Asia"
  },
  {
    "name": "Samarkand",
    "country": "Uzbekistan",
    "region": "Central Asia"
  },
  {
    "name": "Tashkent",
    "country": "Uzbekistan",
    "region": "Central Asia"
  },
  {
    "name": "Bukhara",
    "country": "Uzbekistan",
    "region": "Central Asia"
  },
  {
    "name": "Almaty",
    "country": "Kazakhstan",
    "region": "Central Asia"
  },
  {
    "name": "Bishkek",
    "country": "Kyrgyzstan",
    "region": "Central Asia"
  },
  {
    "name": "Jeddah",
    "country": "Saudi Arabia",
    "region": "Middle East"
  },
  {
    "name": "AlUla",
    "country": "Saudi Arabia",
    "region": "Middle East"
  },
  {
    "name": "Petra",
    "country": "Jordan",
    "region": "Middle East"
  },
  {
    "name": "Wadi Rum",
    "country": "Jordan",
    "region": "Middle East"
  },
  {
    "name": "Jerusalem",
    "country": "Israel",
    "region": "Middle East"
  },
  {
    "name": "Beirut",
    "country": "Lebanon",
    "region": "Middle East"
  },
  {
    "name": "Kuwait City",
    "country": "Kuwait",
    "region": "Middle East"
  },
  {
    "name": "Manama",
    "country": "Bahrain",
    "region": "Middle East"
  },
  {
    "name": "Fez",
    "country": "Morocco",
    "region": "Africa"
  },
  {
    "name": "Chefchaouen",
    "country": "Morocco",
    "region": "Africa"
  },
  {
    "name": "Tangier",
    "country": "Morocco",
    "region": "Africa"
  },
  {
    "name": "Essaouira",
    "country": "Morocco",
    "region": "Africa"
  },
  {
    "name": "Luxor",
    "country": "Egypt",
    "region": "Africa"
  },
  {
    "name": "Aswan",
    "country": "Egypt",
    "region": "Africa"
  },
  {
    "name": "Sharm El Sheikh",
    "country": "Egypt",
    "region": "Africa"
  },
  {
    "name": "Hurghada",
    "country": "Egypt",
    "region": "Africa"
  },
  {
    "name": "Tunis",
    "country": "Tunisia",
    "region": "Africa"
  },
  {
    "name": "Mombasa",
    "country": "Kenya",
    "region": "Africa"
  },
  {
    "name": "Zanzibar",
    "country": "Tanzania",
    "region": "Africa"
  },
  {
    "name": "Arusha",
    "country": "Tanzania",
    "region": "Africa"
  },
  {
    "name": "Kampala",
    "country": "Uganda",
    "region": "Africa"
  },
  {
    "name": "Lalibela",
    "country": "Ethiopia",
    "region": "Africa"
  },
  {
    "name": "Antananarivo",
    "country": "Madagascar",
    "region": "Africa"
  },
  {
    "name": "Victoria",
    "country": "Seychelles",
    "region": "Africa"
  },
  {
    "name": "Port Louis",
    "country": "Mauritius",
    "region": "Africa"
  },
  {
    "name": "Durban",
    "country": "South Africa",
    "region": "Africa"
  },
  {
    "name": "Stellenbosch",
    "country": "South Africa",
    "region": "Africa"
  },
  {
    "name": "Kruger National Park",
    "country": "South Africa",
    "region": "Africa"
  },
  {
    "name": "Victoria Falls",
    "country": "Zimbabwe",
    "region": "Africa"
  },
  {
    "name": "Windhoek",
    "country": "Namibia",
    "region": "Africa"
  },
  {
    "name": "Swakopmund",
    "country": "Namibia",
    "region": "Africa"
  },
  {
    "name": "Gaborone",
    "country": "Botswana",
    "region": "Africa"
  },
  {
    "name": "Maputo",
    "country": "Mozambique",
    "region": "Africa"
  },
  {
    "name": "Dakar",
    "country": "Senegal",
    "region": "Africa"
  },
  {
    "name": "Abidjan",
    "country": "Ivory Coast",
    "region": "Africa"
  },
  {
    "name": "New Orleans",
    "country": "United States",
    "region": "North America"
  },
  {
    "name": "Washington DC",
    "country": "United States",
    "region": "North America"
  },
  {
    "name": "Boston",
    "country": "United States",
    "region": "North America"
  },
  {
    "name": "Nashville",
    "country": "United States",
    "region": "North America"
  },
  {
    "name": "Austin",
    "country": "United States",
    "region": "North America"
  },
  {
    "name": "Seattle",
    "country": "United States",
    "region": "North America"
  },
  {
    "name": "Portland",
    "country": "United States",
    "region": "North America"
  },
  {
    "name": "Denver",
    "country": "United States",
    "region": "North America"
  },
  {
    "name": "San Diego",
    "country": "United States",
    "region": "North America"
  },
  {
    "name": "Savannah",
    "country": "United States",
    "region": "North America"
  },
  {
    "name": "Charleston",
    "country": "United States",
    "region": "North America"
  },
  {
    "name": "Philadelphia",
    "country": "United States",
    "region": "North America"
  },
  {
    "name": "Dallas",
    "country": "United States",
    "region": "North America"
  },
  {
    "name": "Houston",
    "country": "United States",
    "region": "North America"
  },
  {
    "name": "Atlanta",
    "country": "United States",
    "region": "North America"
  },
  {
    "name": "Detroit",
    "country": "United States",
    "region": "North America"
  },
  {
    "name": "Memphis",
    "country": "United States",
    "region": "North America"
  },
  {
    "name": "Anchorage",
    "country": "United States",
    "region": "North America"
  },
  {
    "name": "Montreal",
    "country": "Canada",
    "region": "North America"
  },
  {
    "name": "Quebec City",
    "country": "Canada",
    "region": "North America"
  },
  {
    "name": "Banff",
    "country": "Canada",
    "region": "North America"
  },
  {
    "name": "Victoria",
    "country": "Canada",
    "region": "North America"
  },
  {
    "name": "Ottawa",
    "country": "Canada",
    "region": "North America"
  },
  {
    "name": "Calgary",
    "country": "Canada",
    "region": "North America"
  },
  {
    "name": "Tulum",
    "country": "Mexico",
    "region": "Central America & Caribbean"
  },
  {
    "name": "Oaxaca",
    "country": "Mexico",
    "region": "Central America & Caribbean"
  },
  {
    "name": "Puerto Vallarta",
    "country": "Mexico",
    "region": "Central America & Caribbean"
  },
  {
    "name": "San Miguel de Allende",
    "country": "Mexico",
    "region": "Central America & Caribbean"
  },
  {
    "name": "Guadalajara",
    "country": "Mexico",
    "region": "Central America & Caribbean"
  },
  {
    "name": "Merida",
    "country": "Mexico",
    "region": "Central America & Caribbean"
  },
  {
    "name": "Cabo San Lucas",
    "country": "Mexico",
    "region": "Central America & Caribbean"
  },
  {
    "name": "Monteverde",
    "country": "Costa Rica",
    "region": "Central America & Caribbean"
  },
  {
    "name": "Tamarindo",
    "country": "Costa Rica",
    "region": "Central America & Caribbean"
  },
  {
    "name": "Bocas del Toro",
    "country": "Panama",
    "region": "Central America & Caribbean"
  },
  {
    "name": "Belize City",
    "country": "Belize",
    "region": "Central America & Caribbean"
  },
  {
    "name": "San Pedro",
    "country": "Belize",
    "region": "Central America & Caribbean"
  },
  {
    "name": "Antigua Guatemala",
    "country": "Guatemala",
    "region": "Central America & Caribbean"
  },
  {
    "name": "Lake Atitlan",
    "country": "Guatemala",
    "region": "Central America & Caribbean"
  },
  {
    "name": "San Salvador",
    "country": "El Salvador",
    "region": "Central America & Caribbean"
  },
  {
    "name": "El Tunco",
    "country": "El Salvador",
    "region": "Central America & Caribbean"
  },
  {
    "name": "Tegucigalpa",
    "country": "Honduras",
    "region": "Central America & Caribbean"
  },
  {
    "name": "Roatan",
    "country": "Honduras",
    "region": "Central America & Caribbean"
  },
  {
    "name": "Managua",
    "country": "Nicaragua",
    "region": "Central America & Caribbean"
  },
  {
    "name": "Granada",
    "country": "Nicaragua",
    "region": "Central America & Caribbean"
  },
  {
    "name": "Trinidad",
    "country": "Cuba",
    "region": "Central America & Caribbean"
  },
  {
    "name": "Montego Bay",
    "country": "Jamaica",
    "region": "Central America & Caribbean"
  },
  {
    "name": "Bridgetown",
    "country": "Barbados",
    "region": "Central America & Caribbean"
  },
  {
    "name": "Aruba",
    "country": "Aruba",
    "region": "Central America & Caribbean"
  },
  {
    "name": "Curacao",
    "country": "Curacao",
    "region": "Central America & Caribbean"
  },
  {
    "name": "St. Lucia",
    "country": "Saint Lucia",
    "region": "Central America & Caribbean"
  },
  {
    "name": "Turks and Caicos",
    "country": "Turks and Caicos",
    "region": "Central America & Caribbean"
  },
  {
    "name": "Mendoza",
    "country": "Argentina",
    "region": "South America"
  },
  {
    "name": "Bariloche",
    "country": "Argentina",
    "region": "South America"
  },
  {
    "name": "Ushuaia",
    "country": "Argentina",
    "region": "South America"
  },
  {
    "name": "Salta",
    "country": "Argentina",
    "region": "South America"
  },
  {
    "name": "Salvador",
    "country": "Brazil",
    "region": "South America"
  },
  {
    "name": "Florianopolis",
    "country": "Brazil",
    "region": "South America"
  },
  {
    "name": "Iguazu Falls",
    "country": "Brazil",
    "region": "South America"
  },
  {
    "name": "Recife",
    "country": "Brazil",
    "region": "South America"
  },
  {
    "name": "Fortaleza",
    "country": "Brazil",
    "region": "South America"
  },
  {
    "name": "Valparaiso",
    "country": "Chile",
    "region": "South America"
  },
  {
    "name": "San Pedro de Atacama",
    "country": "Chile",
    "region": "South America"
  },
  {
    "name": "Patagonia",
    "country": "Chile",
    "region": "South America"
  },
  {
    "name": "Cali",
    "country": "Colombia",
    "region": "South America"
  },
  {
    "name": "Santa Marta",
    "country": "Colombia",
    "region": "South America"
  },
  {
    "name": "Machu Picchu",
    "country": "Peru",
    "region": "South America"
  },
  {
    "name": "Arequipa",
    "country": "Peru",
    "region": "South America"
  },
  {
    "name": "Galapagos Islands",
    "country": "Ecuador",
    "region": "South America"
  },
  {
    "name": "Cuenca",
    "country": "Ecuador",
    "region": "South America"
  },
  {
    "name": "Punta del Este",
    "country": "Uruguay",
    "region": "South America"
  },
  {
    "name": "La Paz",
    "country": "Bolivia",
    "region": "South America"
  },
  {
    "name": "Sucre",
    "country": "Bolivia",
    "region": "South America"
  },
  {
    "name": "Uyuni",
    "country": "Bolivia",
    "region": "South America"
  },
  {
    "name": "Asuncion",
    "country": "Paraguay",
    "region": "South America"
  },
  {
    "name": "Georgetown",
    "country": "Guyana",
    "region": "South America"
  },
  {
    "name": "Paramaribo",
    "country": "Suriname",
    "region": "South America"
  },
  {
    "name": "Brisbane",
    "country": "Australia",
    "region": "Oceania"
  },
  {
    "name": "Perth",
    "country": "Australia",
    "region": "Oceania"
  },
  {
    "name": "Gold Coast",
    "country": "Australia",
    "region": "Oceania"
  },
  {
    "name": "Cairns",
    "country": "Australia",
    "region": "Oceania"
  },
  {
    "name": "Adelaide",
    "country": "Australia",
    "region": "Oceania"
  },
  {
    "name": "Hobart",
    "country": "Australia",
    "region": "Oceania"
  },
  {
    "name": "Darwin",
    "country": "Australia",
    "region": "Oceania"
  },
  {
    "name": "Wellington",
    "country": "New Zealand",
    "region": "Oceania"
  },
  {
    "name": "Rotorua",
    "country": "New Zealand",
    "region": "Oceania"
  },
  {
    "name": "Christchurch",
    "country": "New Zealand",
    "region": "Oceania"
  },
  {
    "name": "Bora Bora",
    "country": "French Polynesia",
    "region": "Oceania"
  },
  {
    "name": "Tahiti",
    "country": "French Polynesia",
    "region": "Oceania"
  },
  {
    "name": "Samoa",
    "country": "Samoa",
    "region": "Oceania"
  },
  {
    "name": "Vanuatu",
    "country": "Vanuatu",
    "region": "Oceania"
  },
  {
    "name": "New Caledonia",
    "country": "New Caledonia",
    "region": "Oceania"
  }
]